setup.py
ea/__init__.py
ea/exc.py
ea/utils.py
ea.egg-info/PKG-INFO
ea.egg-info/SOURCES.txt
ea.egg-info/dependency_links.txt
ea.egg-info/requires.txt
ea.egg-info/top_level.txt
ea/blocks/__init__.py
ea/blocks/router/__init__.py
ea/blocks/router/base.py
ea/blocks/router/criterion.py
ea/blocks/router/exc.py
ea/blocks/router/rule.py
ea/blocks/router/schema.py
ea/blocks/router/tests/__init__.py
ea/blocks/router/tests/test_criterion.py
ea/blocks/router/tests/test_router.py
ea/blocks/router/tests/test_rule.py
ea/cqrs/__init__.py
ea/cqrs/exc.py
ea/cqrs/gateway.py
ea/cqrs/command/__init__.py
ea/cqrs/command/handler.py
ea/cqrs/command/issuer.py
ea/cqrs/command/provider.py
ea/cqrs/command/request.py
ea/cqrs/command/result.py
ea/cqrs/command/runner.py
ea/cqrs/command/transport.py
ea/cqrs/command/command/__init__.py
ea/cqrs/command/command/base.py
ea/cqrs/command/command/meta.py
ea/cqrs/command/command/options.py
ea/cqrs/command/issuer/__init__.py
ea/cqrs/command/issuer/base.py
ea/cqrs/command/issuer/local.py
ea/cqrs/command/runner/__init__.py
ea/cqrs/command/runner/base.py
ea/cqrs/command/runner/solo.py
ea/cqrs/command/storage/__init__.py
ea/cqrs/command/storage/base.py
ea/cqrs/command/storage/null.py
ea/cqrs/command/storage/schema.py
ea/cqrs/command/storage/sql/__init__.py
ea/cqrs/command/storage/sql/orm.py
ea/cqrs/query/__init__.py
ea/cqrs/query/base.py
ea/cqrs/query/parameters.py
ea/cqrs/query/result.py
ea/ddd/__init__.py
ea/ddd/aggregate.py
ea/ddd/event.py
ea/ddd/exc.py
ea/ddd/publisher.py
ea/ddd/repository.py
ea/es/__init__.py
ea/es/aggregate.py
ea/es/base.py
ea/es/entity.py
ea/es/exc.py
ea/es/meta.py
ea/es/publisher.py
ea/es/repository.py
ea/es/schema.py
ea/es/storage.py
ea/es/valueobject.py
ea/es/tests/__init__.py
ea/es/tests/aggregate.py
ea/es/tests/test_aggregate.py
ea/es/tests/test_publisher.py
ea/es/tests/test_repository.py
ea/es/tests/test_schema.py
ea/event/__init__.py
ea/event/dispatcher.py
ea/event/dto.py
ea/event/listener.py
ea/event/model.py
ea/event/provider.py
ea/event/publisher.py
ea/event/validator.py
ea/event/contrib/__init__.py
ea/event/contrib/apollo_proton/__init__.py
