Metadata-Version: 1.0
Name: ea
Version: 1.1.7
Summary: Enterprise Architecture Library
Home-page: https://www.wizardsofindustry.net
Author: Cochise Ruhulessin
Author-email: cochiseruhulessin@gmail.com
License: UNKNOWN
Platform: UNKNOWN
